{
  "": "",
  " Lorem ipsum dolor sit amet, consectetur adipisicing elit": {
    " Ipsa, pariatur?": " Ipsa, pariatur?"
  },
  "About Page": "About Page",
  "AboutUS": "AboutUS",
  "Exit": "Exit",
  "HomePage": "HomePage",
  "Incorrect login or password": "Incorrect login or password",
  "Language": "Language",
  "Login": "Login",
  "Lorem ipsum dolor sit amet, consectetur adipisicing elit": {
    " Aliquid corporis ex hic neque nobis omnis saepe, sunt tempora veritatis vitae?": " Aliquid corporis ex hic neque nobis omnis saepe, sunt tempora veritatis vitae?",
    " Beatae consequuntur dicta dolore, eum ipsum necessitatibus nemo non officia optio quisquam?": "Lorem ipsum dolor sit amet, consectetur adipisicing elit. Beatae consequuntur dicta dolore, eum ipsum necessitatibus nemo non officia optio quisquam?"
  },
  "Main Page": "Main Page",
  "Page not found": "Page not found",
  "Password": "Password",
  "Registrant Form": "Registrant Form",
  "Username": "Username",
  "reload page": "reload page",
  "something went wrong": "something went wrong",
  "toggle": "Inchide",
  "trigege error": "trigege error"
}
